JiggleCoord/__init__.py
JiggleCoord/core.py
jigglecoord-0.0.4.dist-info/METADATA
jigglecoord-0.0.4.dist-info/WHEEL
jigglecoord-0.0.4.dist-info/licenses/LICENSE
jigglecoord-0.0.4.dist-info/RECORD
